{
    "package_version": "1.0",
    "id": "d9fb581c-1eed-4d55-a2a6-ce93c1f28276",
    "type": "client-app",
    "name": "app",
    "description": "Description for app",
    "minimum_version": "0070300000",
    "icon_16": "extension-16.png",
    "icon_48": "extension-48.png",
    "icon_128": "extension-128.png",
    "redirect_url": "%serviceURL%",
    "register_url": "%serviceURL%/register",
    "unregister_url": "%serviceURL%/unregister",
    "released_on": "2017-05-15T03:44:30.169Z",
    "service_url": "http://localhost"
}